{
    "index": 0,
    "random": false,
    "sysProxyMode": 0,
    "shareOverLan": false,
    "bypassWhiteList": false,
    "localPort": 1080,
    "localAuthPassword": "EPe09ROaETAwWvlT2FWPXK0yGK",
    "dns_server": "",
    "reconnectTimes": 4,
    "randomAlgorithm": 0,
    "TTL": 60,
    "connect_timeout": 5,
    "proxyRuleMode": 1,
    "proxyEnable": false,
    "pacDirectGoProxy": false,
    "proxyType": 0,
    "proxyHost": "",
    "proxyPort": 0,
    "proxyAuthUser": "",
    "proxyAuthPass": "",
    "proxyUserAgent": "",
    "authUser": "",
    "authPass": "",
    "autoBan": false,
    "sameHostForSameTarget": true,
    "keepVisitTime": 180,
    "isHideTips": true,
    "token": [],
    "portMap": [],
    "configs": [
        {
            "remarks": "\u65b0\u52a0\u5761",
            "server": "128.199.137.247",
            "server_port": 33747,
            "method": "chacha20",
            "obfs": "tls1.2_ticket_auth",
            "obfsparam": "",
            "remarks_base64": "5paw5Yqg5Z2h",
            "password": "q9ETbt",
            "tcp_over_udp": false,
            "udp_over_tcp": false,
            "group": "\u5feb\u4e50\u68af\u5b50",
            "protocol": "auth_sha1_v4",
            "protoparam": "",
            "obfs_udp": false,
            "enable": true
        },
        {
            "remarks": "\u6d1b\u6749\u77f62",
            "server": "llsj.ssvip.link",
            "server_port": 33747,
            "method": "chacha20",
            "obfs": "tls1.2_ticket_auth",
            "obfsparam": "",
            "remarks_base64": "5rSb5p2J55+2Mg==",
            "password": "q9ETbt",
            "tcp_over_udp": false,
            "udp_over_tcp": false,
            "group": "\u5feb\u4e50\u68af\u5b50",
            "protocol": "auth_sha1_v4",
            "protoparam": "",
            "obfs_udp": false,
            "enable": true
        }
    ]
}
